app/__init__.py
app/main.py
app/streamlit_app.py
app/api/__init__.py
app/api/endpoints/__init__.py
app/api/endpoints/prompts.py
app/core/__init__.py
app/core/config.py
app/db/__init__.py
app/db/base_class.py
app/db/init_sqlite.py
app/db/models.py
app/db/session.py
app/schemas/__init__.py
app/schemas/prompt.py
app/scripts/__init__.py
app/scripts/seed_prompts_api.py
exemplar_prompt_hub-0.2.7.dist-info/METADATA
exemplar_prompt_hub-0.2.7.dist-info/WHEEL
exemplar_prompt_hub-0.2.7.dist-info/entry_points.txt
exemplar_prompt_hub-0.2.7.dist-info/top_level.txt
exemplar_prompt_hub-0.2.7.dist-info/RECORD
