Metadata-Version: 2.4
Name: exemplar-prompt-hub
Version: 0.2.7
Summary: A modern REST API service for managing and serving AI prompts
Home-page: https://github.com/shubhanshusingh/exemplar-prompt-hub
Author: Your Name
Author-email: your.email@example.com
License: MIT
Classifier: Development Status :: 4 - Beta
Classifier: Intended Audience :: Developers
Classifier: License :: OSI Approved :: MIT License
Classifier: Operating System :: OS Independent
Classifier: Programming Language :: Python :: 3
Classifier: Programming Language :: Python :: 3.8
Classifier: Programming Language :: Python :: 3.9
Classifier: Programming Language :: Python :: 3.10
Classifier: Programming Language :: Python :: 3.11
Classifier: Topic :: Software Development :: Libraries :: Python Modules
Requires-Python: >=3.8
Requires-Dist: fastapi>=0.104.1
Requires-Dist: uvicorn>=0.24.0
Requires-Dist: sqlalchemy>=2.0.23
Requires-Dist: pydantic>=2.5.2
Requires-Dist: python-multipart==0.0.6
Requires-Dist: python-jose[cryptography]==3.3.0
Requires-Dist: passlib[bcrypt]==1.7.4
Requires-Dist: alembic>=1.12.1
Requires-Dist: python-dotenv>=1.0.0
Requires-Dist: pytest==7.4.3
Requires-Dist: pytest-asyncio==0.21.1
Requires-Dist: httpx==0.25.1
Requires-Dist: pytest-cov==4.1.0
Requires-Dist: pydantic-settings>=2.1.0
Requires-Dist: psycopg2-binary==2.9.9
Requires-Dist: requests==2.31.0
Requires-Dist: streamlit==1.24.0
Requires-Dist: openai==1.60.0
Requires-Dist: openrouter>=0.1.0
Requires-Dist: jinja2>=3.1.2
Dynamic: author
Dynamic: author-email
Dynamic: classifier
Dynamic: description
Dynamic: description-content-type
Dynamic: home-page
Dynamic: license
Dynamic: requires-dist
Dynamic: requires-python
Dynamic: summary
